{"cameraMode":{"drawMode":2,"name":"Shaded Wireframe","section":"Shading Mode"},"sceneLighting":true,"audioPlay":false,"sceneViewState":{"m_AlwaysRefresh":false,"showFog":true,"showSkybox":true,"showFlares":true,"showImageEffects":true,"showParticleSystems":true,"showVisualEffectGraphs":true,"m_FxEnabled":true},"in2DMode":false,"pivot":{"x":3304.061279296875,"y":-1010.677734375,"z":-42.75326919555664},"rotation":{"x":-0.11515091359615326,"y":0.828811764717102,"z":-0.1852595955133438,"w":-0.5152537822723389},"size":5679.13232421875,"orthographic":false}